{
  "assets": {
    "class_spectra": "assets/class_spectra.png",
    "pca_scatter": "assets/pca_scatter.png",
    "spectra_envelope": "assets/spectra_envelope.png",
    "target_distribution": "assets/target_distribution.png",
    "train_test_overlay": "assets/train_test_overlay.png"
  },
  "dimensionality": {
    "cumulative_variance_top10": 0.9986656600102796,
    "effective_rank": 2.0067493828444576,
    "explained_variance_ratio": [
      0.6662476542826438,
      0.21616846075033025,
      0.08638006966532558,
      0.013092616602473671,
      0.006164340513379417,
      0.004374867171811711,
      0.0030129106459388065,
      0.0015240835418280938,
      0.0008773800396463762,
      0.0008232767969021317
    ],
    "imputed": null,
    "n_components_95": 3,
    "n_components_99": 6,
    "n_components_computed": 60,
    "n_features": 2101,
    "n_rows_used": 75,
    "seed": 0
  },
  "identity": {
    "description": "GRAPEVINE_LeafTraits dataset (regression). Auto-generated descriptor (verify before publication).",
    "doi": null,
    "domain": "grapevine_leaftraits",
    "id": "grapevine_leaftraits_wueintr_spxyg70_30_bycultivar_asd",
    "keywords": [
      "grapevine_leaftraits",
      "nir",
      "regression"
    ],
    "license": "LicenseRef-unknown",
    "name": "GRAPEVINE_LeafTraits \u2014 WUEintr_spxyG70_30_byCultivar_ASD",
    "version": "0.1.0",
    "visibility": "restricted"
  },
  "integrity": {
    "content_hash": "2910dab2b9acad794f08f952fc21861260eb83080092d1f6d7fa902106f902a6",
    "descriptor_hash": "8615da9165795e7484aedac1249450384b3427315e6aa75e51418618a10aced5",
    "generated_at": "2026-05-28T21:06:15.165978+00:00",
    "nirs4all_version": "0.9.1"
  },
  "inventory": {
    "metadata_columns": [],
    "n_features": 2101,
    "n_folds": 0,
    "n_samples": 109,
    "n_sources": 1,
    "partitions": {
      "test": 34,
      "train": 75
    },
    "task_type": "regression"
  },
  "per_source": null,
  "quality": {
    "has_nan": false,
    "nan": {
      "has_nan": false,
      "sources": [
        {
          "nan_cells": 0,
          "nan_features": 0,
          "nan_samples": 0,
          "source": 0,
          "total_features": 2101,
          "total_samples": 109
        }
      ],
      "y_nan": 0
    },
    "spectral": {
      "dynamic_range": 0.8166070094660972,
      "noise_proxy_db": 93.37959238335286,
      "saturation_fraction": 6.346184356655561e-06,
      "smoothness": 0.00011136566176142851
    },
    "x_outliers": {
      "distance_stats": {
        "max": 18.245721452215953,
        "mean": 6.4761235217038084,
        "median": 4.917623853178617,
        "min": 3.346973822753577,
        "std": 3.234969474335587
      },
      "exclusion_rate": 0.36,
      "imputed": null,
      "method": "robust_mahalanobis",
      "n_components": 20,
      "n_excluded": 27,
      "n_kept": 48,
      "n_samples": 75,
      "reason": "x_outlier_robust_mahalanobis",
      "threshold": 5.845477474324773
    }
  },
  "schema_version": "1.0",
  "shift": {
    "covariate": {
      "n_components": 10,
      "pc1_ks_p": 0.051417052045332874,
      "pc1_ks_statistic": 0.27098039215686276,
      "pc_space_centroid_distance_std": 0.8041129621447954
    },
    "target": {
      "ks_p": 0.8112508289000891,
      "ks_statistic": 0.12392156862745098,
      "mean_test": 87.51359389810001,
      "mean_train": 91.7810035832723,
      "n_test": 34,
      "n_train": 75,
      "standardized_mean_diff": -0.12051683489849295,
      "std_test": 32.28654980932778,
      "std_train": 38.27802812843291,
      "wasserstein": 7.855694930880676
    }
  },
  "spectral": {
    "n_wavelengths": 2101,
    "signal_type": "unknown",
    "signal_type_confidence": 0.4347826086956522,
    "signal_type_reason": "Range: [0.000, 0.934] | Mean: 0.502 | Detected: reflectance | Confidence: 43.5%",
    "spacing": {
      "is_uniform": true,
      "max": 1.0,
      "mean": 1.0,
      "median": 1.0,
      "min": 1.0,
      "std": 0.0
    },
    "spacing_unit": "nm",
    "wavelength_range": [
      400.0,
      2500.0
    ],
    "wavelength_unit": "nm"
  },
  "targets": {
    "partitions": {
      "test": {
        "cv": 0.3634658650393135,
        "max": 154.52853393554688,
        "mean": 87.51359389810001,
        "median": 84.4783935546875,
        "min": 32.734230041503906,
        "nsample": 34,
        "sd": 31.808204108872108
      },
      "train": {
        "cv": 0.41426856809620344,
        "max": 187.5735321044922,
        "mean": 91.7810035832723,
        "median": 89.07946014404297,
        "min": 14.1311674118042,
        "nsample": 75,
        "sd": 38.02198493287473
      }
    },
    "shape": {
      "is_normal": true,
      "kurtosis": 0.024281050288525563,
      "n": 109,
      "normality_p": 0.10996845125437937,
      "skewness": 0.4896078730479873
    },
    "stats": {
      "cv": 0.40080026121551443,
      "max": 187.5735321044922,
      "mean": 90.44988496587911,
      "median": 88.50186157226562,
      "min": 14.1311674118042,
      "nsample": 109,
      "sd": 36.25233752123758
    },
    "task_type": "regression"
  },
  "warnings": []
}