{
  "assets": {
    "class_spectra": "assets/class_spectra.png",
    "pca_scatter": "assets/pca_scatter.png",
    "spectra_envelope": "assets/spectra_envelope.png",
    "target_distribution": "assets/target_distribution.png",
    "train_test_overlay": "assets/train_test_overlay.png"
  },
  "dimensionality": {
    "cumulative_variance_top10": 0.9989427016385205,
    "effective_rank": 1.9666041043584295,
    "explained_variance_ratio": [
      0.669211304975084,
      0.23855238568745565,
      0.056448648411717824,
      0.02190024714449522,
      0.00708524845068045,
      0.0024750795967192203,
      0.001425667089565954,
      0.0008963718621490521,
      0.0005450953567933711,
      0.000402653063859814
    ],
    "imputed": null,
    "n_components_95": 3,
    "n_components_99": 5,
    "n_components_computed": 60,
    "n_features": 401,
    "n_rows_used": 276,
    "seed": 0
  },
  "identity": {
    "description": "DIESEL dataset (regression). Auto-generated descriptor (verify before publication).",
    "doi": null,
    "domain": "diesel",
    "id": "diesel_visc_395_pengks",
    "keywords": [
      "diesel",
      "nir",
      "regression"
    ],
    "license": "LicenseRef-unknown",
    "name": "DIESEL \u2014 DIESEL_VISC_395_PengKS",
    "version": "0.1.0",
    "visibility": "restricted"
  },
  "integrity": {
    "content_hash": "1241cd85b2b7ce4c8adfff71bfd7509e97756ad6a0b2f8d92ce2774a89371aa9",
    "descriptor_hash": "af89b6f035ec8986f3c531ddba715e9f356af029ca4ac763334c4d9d81518e2c",
    "generated_at": "2026-06-11T00:44:38.124850+00:00",
    "metadata_hash": "bd9c76c9f43e10d21e8e5d845486eb4443e30a5930519ab4188b6d75b0691f51",
    "nirs4all_version": "0.9.3",
    "traceability": {
      "canonical_sha256": {
        "Xtest.parquet": "379e74317b8ee2615e6bed562546a69d9c99fceec31256e248c5c55c7deb2327",
        "Xtrain.parquet": "a614e391b6a84ef972bf519949d12bef3c43ec4d77dd6a764158089541a65b17",
        "Ytest.parquet": "eaf1a572c50ff5893d2561e55fd0c12e28b7192c61f591d55e7f747fe7f860fe",
        "Ytrain.parquet": "0d35e906abe0fb486028d53be771d6f706892322b22dc739bfff54b6598c1d4d"
      },
      "manifest_fresh": true,
      "origin_locators": [
        "https://eigenvector.com/resources/data-sets/"
      ],
      "raw_sha256": [
        "be18dd49c9dddd941c114b004b3463b0a699fe8b5629f2e07488697b9f664aa3",
        "e5a73cdd48b877895a5071c5e64240734479e99dc37aef7d368e2a7d3dd54a88",
        "428cca6a6039c223094731d4c94b48007c9c1f75ad50a1a604ddac67a606be64",
        "3fee1526299c9d25bdf16e101d97f274d1449b82daa994676046fffd274c33a1"
      ]
    }
  },
  "inventory": {
    "metadata_columns": [],
    "n_features": 401,
    "n_folds": 0,
    "n_samples": 395,
    "n_sources": 1,
    "partitions": {
      "test": 119,
      "train": 276
    },
    "task_type": "regression"
  },
  "per_source": null,
  "provenance": {
    "citation": "https://doi.org/10.1016/j.chemolab.2018.09.009",
    "contributor": "NIRS DB reference collection",
    "dataset_version": null,
    "publications": [
      {
        "authors": [],
        "citation": null,
        "doi": "10.1016/j.chemolab.2018.09.009",
        "title": null,
        "year": null
      }
    ],
    "reference_method": null,
    "republished_doi": null,
    "sources": [
      {
        "access": "manual",
        "kind": "url",
        "license": null,
        "locator": "https://eigenvector.com/resources/data-sets/",
        "mode": "raw",
        "title": null
      }
    ]
  },
  "quality": {
    "has_nan": false,
    "nan": {
      "has_nan": false,
      "sources": [
        {
          "nan_cells": 0,
          "nan_features": 0,
          "nan_samples": 0,
          "source": 0,
          "total_features": 401,
          "total_samples": 395
        }
      ],
      "y_nan": 0
    },
    "spectral": {
      "dynamic_range": 1.0777232794925562,
      "noise_proxy_db": 57.11883813818464,
      "saturation_fraction": 9.035382558097509e-06,
      "smoothness": 0.00312656587924331
    },
    "x_outliers": {
      "distance_stats": {
        "max": 80.81236210977484,
        "mean": 7.187141617040138,
        "median": 5.143120468829768,
        "min": 2.3704284417379626,
        "std": 7.2707543598519235
      },
      "exclusion_rate": 0.42391304347826086,
      "imputed": null,
      "method": "robust_mahalanobis",
      "n_components": 20,
      "n_excluded": 117,
      "n_kept": 159,
      "n_samples": 276,
      "reason": "x_outlier_robust_mahalanobis",
      "threshold": 5.845477474324773
    }
  },
  "schema_version": "1.0",
  "shift": {
    "covariate": {
      "n_components": 10,
      "pc1_ks_p": 3.6586775913294934e-07,
      "pc1_ks_statistic": 0.3009377664109122,
      "pc_space_centroid_distance_std": 1.1870638735215249
    },
    "target": {
      "ks_p": 0.0024074991055426094,
      "ks_statistic": 0.19817927170868346,
      "mean_test": 2.538991593513168,
      "mean_train": 2.5073913080968717,
      "n_test": 119,
      "n_train": 276,
      "standardized_mean_diff": 0.06566059821442141,
      "std_test": 0.3334600226813965,
      "std_train": 0.5933299658907177,
      "wasserstein": 0.21922361052598136
    }
  },
  "spectral": {
    "n_wavelengths": 401,
    "signal_type": "absorbance",
    "signal_type_confidence": 0.8947368421052632,
    "signal_type_reason": "Range: [-0.049, 1.188] | Mean: 0.132 | Detected: absorbance | Confidence: 89.5%",
    "spacing": {
      "is_uniform": true,
      "max": 2.0,
      "mean": 2.0,
      "median": 2.0,
      "min": 2.0,
      "std": 0.0
    },
    "spacing_unit": "nm",
    "wavelength_range": [
      750.0,
      1550.0
    ],
    "wavelength_unit": "nm"
  },
  "targets": {
    "partitions": {
      "test": {
        "cv": 0.13078262058563406,
        "max": 3.9200000762939453,
        "mean": 2.538991593513168,
        "median": 2.559999942779541,
        "min": 1.3799999952316284,
        "nsample": 119,
        "sd": 0.3320559742445471
      },
      "train": {
        "cv": 0.23620330638733195,
        "max": 4.050000190734863,
        "mean": 2.5073913080968717,
        "median": 2.6049998998641968,
        "min": 1.1200000047683716,
        "nsample": 276,
        "sd": 0.5922541173793384
      }
    },
    "shape": {
      "is_normal": false,
      "kurtosis": 0.64419933552188,
      "n": 395,
      "normality_p": 1.001095527098163e-05,
      "skewness": -0.5520426527108458
    },
    "stats": {
      "cv": 0.20968141473277083,
      "max": 4.050000190734863,
      "mean": 2.5169113940830474,
      "median": 2.5799999237060547,
      "min": 1.1200000047683716,
      "nsample": 395,
      "sd": 0.5277495418683639
    },
    "task_type": "regression"
  },
  "warnings": []
}