{
  "assets": {
    "class_spectra": "assets/class_spectra.png",
    "pca_scatter": "assets/pca_scatter.png",
    "spectra_envelope": "assets/spectra_envelope.png",
    "target_distribution": "assets/target_distribution.png",
    "train_test_overlay": "assets/train_test_overlay.png"
  },
  "dimensionality": {
    "cumulative_variance_top10": 0.998867044622947,
    "effective_rank": 1.82659377936589,
    "explained_variance_ratio": [
      0.7102841116129935,
      0.19877643038306186,
      0.053225144736284244,
      0.023467736692887563,
      0.0063501020954180995,
      0.002465061147554244,
      0.0018568511244065563,
      0.0014323130017183793,
      0.0005755669750490511,
      0.00043372685357335073
    ],
    "imputed": null,
    "n_components_95": 3,
    "n_components_99": 5,
    "n_components_computed": 60,
    "n_features": 401,
    "n_rows_used": 276,
    "seed": 0
  },
  "identity": {
    "description": "DIESEL dataset (regression). Auto-generated descriptor (verify before publication).",
    "doi": null,
    "domain": "diesel",
    "id": "diesel_flash_395_pengks",
    "keywords": [
      "diesel",
      "nir",
      "regression"
    ],
    "license": "LicenseRef-unknown",
    "name": "DIESEL \u2014 DIESEL_FLASH_395_PengKS",
    "version": "0.1.0",
    "visibility": "restricted"
  },
  "integrity": {
    "content_hash": "d217d1a0ee58c85ac9034a308daf503ac2485e2d0b968956065e15b03e276eae",
    "descriptor_hash": "7732461c0be7ada78767f3a991fb907a76641286b32caad8063a9499e8d6c777",
    "generated_at": "2026-06-11T00:42:39.405070+00:00",
    "metadata_hash": "3c97a6dcfa754d8dc0543d338c2be83c2808887fd171eaf0b995687d02e508f4",
    "nirs4all_version": "0.9.3",
    "traceability": {
      "canonical_sha256": {
        "Xtest.parquet": "bb31f37076ffd943cecd399531bbde49779e6ea4c10f061b89936a46c277166b",
        "Xtrain.parquet": "8713e37a99600fec1ccda7b1f2bca465dd17d9e0e5c4eb27002fc6aaaa775d7c",
        "Ytest.parquet": "5ac3cf89279be337d85f0127441f1a8f523eafd84229775d72c0ce360d0ab138",
        "Ytrain.parquet": "29f7a1ab5433eecc54b1a7ba5e5e6c2153a4d2af1caf7f4654466126ae94bde9"
      },
      "manifest_fresh": true,
      "origin_locators": [
        "https://eigenvector.com/resources/data-sets/"
      ],
      "raw_sha256": [
        "e05fd30f5781f6ca60cc64730a5d6c58bde21e6d66496f46f3d3f9eede371c5b",
        "f994212dbac9203e4af317c29f07980924e179e7deed0e05f127eae4158e34a9",
        "f027954871e6394edbc16d7969daa0111f20435b610015959d863d35343ef2b3",
        "bb118131ad5e6f929ff153a39bf5e41d93f6103d746dcd04f3912ea19791e0a7"
      ]
    }
  },
  "inventory": {
    "metadata_columns": [],
    "n_features": 401,
    "n_folds": 0,
    "n_samples": 395,
    "n_sources": 1,
    "partitions": {
      "test": 119,
      "train": 276
    },
    "task_type": "regression"
  },
  "per_source": null,
  "provenance": {
    "citation": "https://doi.org/10.1016/j.chemolab.2018.09.009",
    "contributor": "NIRS DB reference collection",
    "dataset_version": null,
    "publications": [
      {
        "authors": [],
        "citation": null,
        "doi": "10.1016/j.chemolab.2018.09.009",
        "title": null,
        "year": null
      }
    ],
    "reference_method": null,
    "republished_doi": null,
    "sources": [
      {
        "access": "manual",
        "kind": "url",
        "license": null,
        "locator": "https://eigenvector.com/resources/data-sets/",
        "mode": "raw",
        "title": null
      }
    ]
  },
  "quality": {
    "has_nan": false,
    "nan": {
      "has_nan": false,
      "sources": [
        {
          "nan_cells": 0,
          "nan_features": 0,
          "nan_samples": 0,
          "source": 0,
          "total_features": 401,
          "total_samples": 395
        }
      ],
      "y_nan": 0
    },
    "spectral": {
      "dynamic_range": 1.0785256375681351,
      "noise_proxy_db": 57.03543086273919,
      "saturation_fraction": 1.8070765116195018e-05,
      "smoothness": 0.0031259781613104153
    },
    "x_outliers": {
      "distance_stats": {
        "max": 121.76861364734364,
        "mean": 7.891418406987286,
        "median": 5.018034200855151,
        "min": 2.1165652985013694,
        "std": 10.480248627183464
      },
      "exclusion_rate": 0.39855072463768115,
      "imputed": null,
      "method": "robust_mahalanobis",
      "n_components": 20,
      "n_excluded": 110,
      "n_kept": 166,
      "n_samples": 276,
      "reason": "x_outlier_robust_mahalanobis",
      "threshold": 5.845477474324773
    }
  },
  "schema_version": "1.0",
  "shift": {
    "covariate": {
      "n_components": 10,
      "pc1_ks_p": 2.044429665484729e-06,
      "pc1_ks_statistic": 0.28388746803069054,
      "pc_space_centroid_distance_std": 1.1961140526547138
    },
    "target": {
      "ks_p": 0.27252185467436507,
      "ks_statistic": 0.10699062233589088,
      "mean_test": 25.025210084033613,
      "mean_train": 24.380434782608695,
      "n_test": 119,
      "n_train": 276,
      "standardized_mean_diff": 0.08027209627734028,
      "std_test": 7.162120442658842,
      "std_train": 8.817143290787367,
      "wasserstein": 1.7371513822920468
    }
  },
  "spectral": {
    "n_wavelengths": 401,
    "signal_type": "absorbance",
    "signal_type_confidence": 0.8947368421052632,
    "signal_type_reason": "Range: [-0.049, 1.145] | Mean: 0.132 | Detected: absorbance | Confidence: 89.5%",
    "spacing": {
      "is_uniform": true,
      "max": 2.0,
      "mean": 2.0,
      "median": 2.0,
      "min": 2.0,
      "std": 0.0
    },
    "spacing_unit": "nm",
    "wavelength_range": [
      750.0,
      1550.0
    ],
    "wavelength_unit": "nm"
  },
  "targets": {
    "partitions": {
      "test": {
        "cv": 0.28499117442648636,
        "max": 49.0,
        "mean": 25.025210084033613,
        "median": 24.0,
        "min": 3.0,
        "nsample": 119,
        "sd": 7.1319640121182895
      },
      "train": {
        "cv": 0.3609925659221119,
        "max": 48.0,
        "mean": 24.380434782608695,
        "median": 25.0,
        "min": 0.0,
        "nsample": 276,
        "sd": 8.801155710470619
      }
    },
    "shape": {
      "is_normal": false,
      "kurtosis": 0.7843894002829597,
      "n": 395,
      "normality_p": 0.012378621325734225,
      "skewness": -0.18907040303240344
    },
    "stats": {
      "cv": 0.3393247589954467,
      "max": 49.0,
      "mean": 24.5746835443038,
      "median": 25.0,
      "min": 0.0,
      "nsample": 395,
      "sd": 8.338798571060256
    },
    "task_type": "regression"
  },
  "warnings": []
}